odoo/addons/hr_attendance_overtime_manual/README.rst
odoo/addons/hr_attendance_overtime_manual/__init__.py
odoo/addons/hr_attendance_overtime_manual/__manifest__.py
odoo/addons/hr_attendance_overtime_manual/i18n/de.po
odoo/addons/hr_attendance_overtime_manual/i18n/hr_attendance_overtime_manual.pot
odoo/addons/hr_attendance_overtime_manual/models/__init__.py
odoo/addons/hr_attendance_overtime_manual/models/hr_attendance_overtime.py
odoo/addons/hr_attendance_overtime_manual/readme/CONTRIBUTORS.rst
odoo/addons/hr_attendance_overtime_manual/readme/DESCRIPTION.rst
odoo/addons/hr_attendance_overtime_manual/security/ir.model.access.csv
odoo/addons/hr_attendance_overtime_manual/static/description/icon.png
odoo/addons/hr_attendance_overtime_manual/static/description/index.html
odoo/addons/hr_attendance_overtime_manual/tests/__init__.py
odoo/addons/hr_attendance_overtime_manual/tests/test_wizard.py
odoo/addons/hr_attendance_overtime_manual/views/hr_attendance_overtime_views.xml
odoo/addons/hr_attendance_overtime_manual/views/hr_employee_views.xml
odoo/addons/hr_attendance_overtime_manual/wizard/__init__.py
odoo/addons/hr_attendance_overtime_manual/wizard/hr_attendance_overtime_manual_wizard.py
odoo/addons/hr_attendance_overtime_manual/wizard/hr_attendance_overtime_manual_wizard_views.xml
odoo_addon_hr_attendance_overtime_manual-15.0.1.0.0.2.dist-info/METADATA
odoo_addon_hr_attendance_overtime_manual-15.0.1.0.0.2.dist-info/WHEEL
odoo_addon_hr_attendance_overtime_manual-15.0.1.0.0.2.dist-info/top_level.txt
odoo_addon_hr_attendance_overtime_manual-15.0.1.0.0.2.dist-info/RECORD
